pybun/__init__.py
pybun/__main__.py
pybun/bootstrap.py
pybun/cli.py
pybun_cli-0.1.15.dist-info/licenses/LICENSE
pybun_cli-0.1.15.dist-info/METADATA
pybun_cli-0.1.15.dist-info/WHEEL
pybun_cli-0.1.15.dist-info/entry_points.txt
pybun_cli-0.1.15.dist-info/top_level.txt
pybun_cli-0.1.15.dist-info/RECORD
