Metadata-Version: 2.4
Name: pybun-cli
Version: 0.1.15
Summary: PyBun shim bootstrapper for signed releases
Author: PyBun Authors
License-Expression: MIT
Project-URL: Homepage, https://github.com/VOID-TECHNOLOGY-INC/PyBun
Project-URL: Repository, https://github.com/VOID-TECHNOLOGY-INC/PyBun
Classifier: Programming Language :: Python :: 3
Classifier: Programming Language :: Python :: 3 :: Only
Classifier: Programming Language :: Python :: 3.8
Classifier: Programming Language :: Python :: 3.9
Classifier: Programming Language :: Python :: 3.10
Classifier: Programming Language :: Python :: 3.11
Classifier: Programming Language :: Python :: 3.12
Requires-Python: >=3.8
License-File: LICENSE
Dynamic: license-file
